pybind11_cubao_cmake_example.cpython-39-aarch64-linux-gnu.so
cubao_cmake_example-0.0.3.dist-info/top_level.txt
cubao_cmake_example-0.0.3.dist-info/LICENSE
cubao_cmake_example-0.0.3.dist-info/RECORD
cubao_cmake_example-0.0.3.dist-info/WHEEL
cubao_cmake_example-0.0.3.dist-info/METADATA
cubao_cmake_example/__main__.py
cubao_cmake_example/__init__.py
