Metadata-Version: 2.1
Name: cubao-cmake-example
Version: 0.0.3
Summary: A test project using pybind11 and CMake
Home-page: https://cmake-example.readthedocs.io
Author: tzx
Author-email: dvorak4tzx@gmail.com
License: UNKNOWN
Platform: UNKNOWN
Requires-Python: >=3.6
License-File: LICENSE
Requires-Dist: fire
Provides-Extra: test
Requires-Dist: pytest (>=6.0) ; extra == 'test'
